{
  "variants": {
    "face=ceiling,facing=east": {
      "model": "simpeladdmod:block/chunk_torch",
      "x": 180,
      "y": 270
    },
    
    "face=ceiling,facing=north": {
      "model": "simpeladdmod:block/chunk_torch",
      "x": 180,
      "y": 180
    },
    
    "face=ceiling,facing=south": {
      "model": "simpeladdmod:block/chunk_torch",
      "x": 180
    },
    
    "face=ceiling,facing=west": {
      "model": "simpeladdmod:block/chunk_torch",
      "x": 180,
      "y": 90
    },

    "face=floor,facing=east": {
      "model": "simpeladdmod:block/chunk_torch",
      "y": 90
    },

    "face=floor,facing=north": {
      "model": "simpeladdmod:block/chunk_torch"
    },
    "face=floor,facing=south": {
      "model": "simpeladdmod:block/chunk_torch",
      "y": 180
    },

    "face=floor,facing=west": {
      "model": "simpeladdmod:block/chunk_torch",
      "y": 270
    },
    
    "face=wall,facing=east": {
      "model": "simpeladdmod:block/chunk_torch",
      "uvlock": true,
      "x": 90,
      "y": 90
    },

    "face=wall,facing=north": {
      "model": "simpeladdmod:block/chunk_torch",
      "uvlock": true,
      "x": 90
    },

    "face=wall,facing=south": {
      "model": "simpeladdmod:block/chunk_torch",
      "uvlock": true,
      "x": 90,
      "y": 180
    },

    "face=wall,facing=west": {
      "model": "simpeladdmod:block/chunk_torch",
      "uvlock": true,
      "x": 90,
      "y": 270
    }
  }
}